Workbook
Name aporte: Simulador!$D$21
Name patrimonio: Simulador!$D$24
Name qtd_anos: Simulador!$D$22
Name rendimento_carteira: Simulador!$D$16
Name salario: Simulador!$D$15
Name sugestao_de_investimento: Simulador!$D$17
Name taxa_mensal: Simulador!$D$23

Sheet Simulador
B14: CONFIGURAÇÕES
B15: Salário | D15: 5000
B16: Rendimento Carteira | D16: 0.01
B17: Sugestão de Investimento | D17: =D15*30% -> 1500
B20: INVESTIMENTO MENSAL
B21: Investimento mensal | D21: 1260
B22: Tempo necessário de investimento (anos) | D22: 10
B23: Taxa de rendimento mensal | D23: 0.01079
B24: Patrimônio final acumulado | D24: =FV(taxa_mensal,qtd_anos*12,aporte*-1) -> 306538.11
B25: Valor dos dividendos mensais | D25: =D24*1% -> 3065.3811
B27: CENÁRIOS | D27: Dividendos
A28: 2 | B28: Patrimônio em 2 anos | C28: =FV($D$23,$A28*12,$D$21*-1) -> 34306.81 | D28: =C28*rendimento_carteira -> 343.0681
A29: 5 | B29: Patrimônio em 5 anos | C29: =FV($D$23,$A29*12,$D$21*-1) -> 105558.91 | D29: =C29*rendimento_carteira -> 1055.5891
A30: 10 | B30: Patrimônio em 10 anos | C30: =FV($D$23,$A30*12,$D$21*-1) -> 306538.11 | D30: =C30*rendimento_carteira -> 3065.3811
A31: 20 | B31: Patrimônio em 20 anos | C31: =FV($D$23,$A31*12,$D$21*-1) -> 1417750 | D31: =C31*rendimento_carteira -> 14177.5
A32: 30 | B32: Patrimônio em 30 anos | C32: =FV($D$23,$A32*12,$D$21*-1) -> 5445933.8 | D32: =C32*rendimento_carteira -> 54459.338
B34: Perfil | C34: CONSERVADOR
B35: VALOR A SER INVESTIDO POR MÊS | C35: =aporte -> 1260
B37: TIPO DE FII | C37: Percentual Sugerido | D37: Valores
B38: PAPEL | C38: =VLOOKUP($C$34&"-"&B38,Plan3!A:D,4,FALSE) -> 0.3 | D38: =C38*$C$35 -> 378
B39: TIJOLO | C39: =VLOOKUP($C$34&"-"&B39,Plan3!A:D,4,FALSE) -> 0.5 | D39: =C39*$C$35 -> 630
B40: HÍBRIDO | C40: =VLOOKUP($C$34&"-"&B40,Plan3!A:D,4,FALSE) -> 0.1 | D40: =C40*$C$35 -> 126
B41: FOF's | C41: =VLOOKUP($C$34&"-"&B41,Plan3!A:D,4,FALSE) -> 0.1 | D41: =C41*$C$35 -> 126
B42: DESENVOLVIMENTO | C42: =VLOOKUP($C$34&"-"&B42,Plan3!A:D,4,FALSE) -> 0 | D42: =C42*$C$35 -> 0
B43: HOTELARIA | C43: =VLOOKUP($C$34&"-"&B43,Plan3!A:D,4,FALSE) -> 0 | D43: =C43*$C$35 -> 0
B44: TOTAL | D44: =SUM(D38:D43) -> 1260

Sheet Plan3
A3: CHAVE | B3: PERFIL | C3: TIPOS DE FII | D3: %
A4: =B4&"-"&C4 -> CONSERVADOR-PAPEL | B4: CONSERVADOR | C4: PAPEL | D4: 0.3 | H4: %
A5: =B5&"-"&C5 -> CONSERVADOR-TIJOLO | B5: CONSERVADOR | C5: TIJOLO | D5: 0.5 | G5: MODERADO-TIJOLO | H5: =VLOOKUP(G5,$A:$D,4,FALSE) -> 0.35
A6: =B6&"-"&C6 -> CONSERVADOR-HÍBRIDO | B6: CONSERVADOR | C6: HÍBRIDO | D6: 0.1
A7: =B7&"-"&C7 -> CONSERVADOR-FOF's | B7: CONSERVADOR | C7: FOF's | D7: 0.1
A8: =B8&"-"&C8 -> CONSERVADOR-DESENVOLVIMENTO | B8: CONSERVADOR | C8: DESENVOLVIMENTO | D8: 0
A9: =B9&"-"&C9 -> CONSERVADOR-HOTELARIA | B9: CONSERVADOR | C9: HOTELARIA | D9: 0
A10: =B10&"-"&C10 -> MODERADO-PAPEL | B10: MODERADO | C10: PAPEL | D10: 0.32
A11: =B11&"-"&C11 -> MODERADO-TIJOLO | B11: MODERADO | C11: TIJOLO | D11: 0.35
A12: =B12&"-"&C12 -> MODERADO-HÍBRIDO | B12: MODERADO | C12: HÍBRIDO | D12: 0.08
A13: =B13&"-"&C13 -> MODERADO-FOF's | B13: MODERADO | C13: FOF's | D13: 0.05
A14: =B14&"-"&C14 -> MODERADO-DESENVOLVIMENTO | B14: MODERADO | C14: DESENVOLVIMENTO | D14: 0.1
A15: =B15&"-"&C15 -> MODERADO-HOTELARIA | B15: MODERADO | C15: HOTELARIA | D15: 0.1
A16: =B16&"-"&C16 -> AGRESSIVO-PAPEL | B16: AGRESSIVO | C16: PAPEL | D16: 0.5
A17: =B17&"-"&C17 -> AGRESSIVO-TIJOLO | B17: AGRESSIVO | C17: TIJOLO | D17: 0.1
... A21: =B21&"-"&C21 -> AGRESSIVO-HOTELARIA | B21: AGRESSIVO | C21: HOTELARIA | D21: 0.1

Sheet Problema e Perguntas de Negócio
B2: Criar um simulador simples de investimentos
A3: 1 | B3: Quanto investir por mês?
A4: 2 | B4: Por quantos anos precisa investir?
A5: 3 | B5: Qual a taxa de rendimento mensal?
A6: 4 | B6: Qual o patrimônio acumulado terá no final?
A7: 5 | B7: Qual o valor dos dividendos mensais?
